sifty/__init__.py
sifty/filesystem.py
sifty/filesystem.pyi
sifty/typing/__init__.py
sifty/typing/typing.py
sifty/typing/typing.pyi
sifty-1.0.5.dist-info/LICENSE.txt
sifty-1.0.5.dist-info/METADATA
sifty-1.0.5.dist-info/WHEEL
sifty-1.0.5.dist-info/top_level.txt
sifty-1.0.5.dist-info/RECORD
