Metadata-Version: 2.1
Name: sifty
Version: 1.0.5
Summary: Sifty is a powerful, lightweight Python library designed for providing many different functions.
Author: Sifty Developers
License: MIT License
Project-URL: source, https://github.com/DevByEagle/sifty
Project-URL: tracker, https://github.com/DevByEagle/sifty/issues
Classifier: Development Status :: 3 - Alpha
Classifier: License :: OSI Approved :: MIT License
Classifier: Intended Audience :: Developers
Classifier: Programming Language :: Python :: 3
Classifier: Programming Language :: Python :: 3.10
Classifier: Programming Language :: Python :: 3.11
Classifier: Programming Language :: Python :: 3.12
Classifier: Programming Language :: Python :: 3.13
Classifier: Topic :: Software Development
Requires-Python: >=3.10
License-File: LICENSE.txt
Requires-Dist: typing
Provides-Extra: dev
